akio/__init__.py
akio/config/__init__.py
akio/config/constants.py
akio/config/init.py
akio/config/settings.py
akio/lib/__init__.py
akio/lib/api/__init__.py
akio/lib/api/routes.py
akio/lib/mcp/__init__.py
akio/lib/mcp/client.py
akio/lib/mcp/server.py
akio/lib/tools/__init__.py
akio/lib/tools/browser.py
akio/lib/tools/code.py
akio/lib/tools/message.py
akio/lib/tools/rag.py
akio/lib/tools/shell.py
akio/lib/tools/web_search.py
akio/lib/tui/__init__.py
akio/lib/tui/app.py
akio/lib/utils/__init__.py
akio/lib/utils/cli.py
akio/lib/utils/env.py
akio/lib/utils/voice.py
akio/main.py
akio-0.0.3.dev0.dist-info/WHEEL
akio-0.0.3.dev0.dist-info/entry_points.txt
akio-0.0.3.dev0.dist-info/METADATA
akio-0.0.3.dev0.dist-info/RECORD
