Metadata-Version: 2.3
Name: akio
Version: 0.0.3.dev0
Summary: An agentic AI for red team tasks.
Keywords: ai,llm,agent,autonomous,pentest,redteam,local,rag,mcp
Author: Fastiraz
Classifier: Programming Language :: Python :: 3
Classifier: Development Status :: 2 - Pre-Alpha
Classifier: Operating System :: POSIX :: Linux
Classifier: Operating System :: Unix
Classifier: Operating System :: MacOS
Classifier: Topic :: Security
Classifier: Topic :: Scientific/Engineering :: Artificial Intelligence
Requires-Dist: asyncio>=3.4.3
Requires-Dist: browser-use>=0.7.10
Requires-Dist: chromadb>=0.5.23
Requires-Dist: fastapi[standard]>=0.116.1
Requires-Dist: mcp[cli]>=1.9.2
Requires-Dist: ollama>=0.5.1
Requires-Dist: openai-whisper>=20250625
Requires-Dist: playwright>=1.52.0
Requires-Dist: pydantic>=2.10.6
Requires-Dist: rich>=13.9.4
Requires-Dist: watchdog>=6.0.0
Maintainer: Fastiraz
Requires-Python: >=3.11
Project-URL: documentation, https://fastiraz.github.io/grimoire/
Project-URL: homepage, https://github.com/fastiraz/akio
Project-URL: issues, https://github.com/Fastiraz/akio/issues
Project-URL: repository, https://github.com/fastiraz/akio
